odoo/addons/stock_inventory_valuation_unit_cost/README.rst
odoo/addons/stock_inventory_valuation_unit_cost/__init__.py
odoo/addons/stock_inventory_valuation_unit_cost/__manifest__.py
odoo/addons/stock_inventory_valuation_unit_cost/i18n/stock_inventory_valuation_unit_cost.pot
odoo/addons/stock_inventory_valuation_unit_cost/readme/CONTRIBUTORS.rst
odoo/addons/stock_inventory_valuation_unit_cost/readme/DESCRIPTION.rst
odoo/addons/stock_inventory_valuation_unit_cost/static/description/icon.png
odoo/addons/stock_inventory_valuation_unit_cost/static/description/index.html
odoo/addons/stock_inventory_valuation_unit_cost/views/stock_valuation_layer_views.xml
odoo13_addon_stock_inventory_valuation_unit_cost-13.0.1.0.1.dev3.dist-info/METADATA
odoo13_addon_stock_inventory_valuation_unit_cost-13.0.1.0.1.dev3.dist-info/WHEEL
odoo13_addon_stock_inventory_valuation_unit_cost-13.0.1.0.1.dev3.dist-info/top_level.txt
odoo13_addon_stock_inventory_valuation_unit_cost-13.0.1.0.1.dev3.dist-info/RECORD
